[
    {
        "question": "A critical bug has been identified in our system. Let's create a work item to address it. The details are as follows:\n\nType of Work: Issue\nTitle: Resolve Critical System Bug\nDescription: This issue involves fixing a critical bug in the system that is impacting performance.\nAssignee: AMZ-987\nPriority: High\nDue Date: 2023-12-15\nTags: ['bug', 'critical', 'urgent']\n\nCan you proceed with creating this work item?",
        "answer": [
            {
                "tool_name": "create_work_item",
                "arguments": [
                    {
                        "name": "work_item_type",
                        "value": "issue"
                    },
                    {
                        "name": "title",
                        "value": "Resolve Critical System Bug"
                    },
                    {
                        "name": "description",
                        "value": "This issue involves fixing a critical bug in the system that is impacting performance."
                    },
                    {
                        "name": "assignee",
                        "value": "AMZ-987"
                    },
                    {
                        "name": "priority",
                        "value": "high"
                    },
                    {
                        "name": "due_date",
                        "value": "2023-12-15"
                    },
                    {
                        "name": "tags",
                        "value": [
                            "bug",
                            "critical",
                            "urgent"
                        ]
                    }
                ]
            }
        ]
    },
    {
        "question": "Our project requires a new task related to database optimization. Provide the details for creating this work item:\n\nType of Work: Task\nTitle: Optimize Database Performance\nDescription: This task involves optimizing database queries for better performance.\nAssignee: FPK-567\nPriority: Medium\nDue Date: 2023-11-20\nTags: ['performance', 'database']\n\nCould you create this task?",
        "answer": [
            {
                "tool_name": "create_work_item",
                "arguments": [
                    {
                        "name": "work_item_type",
                        "value": "task"
                    },
                    {
                        "name": "title",
                        "value": "Optimize Database Performance"
                    },
                    {
                        "name": "description",
                        "value": "This task involves optimizing database queries for better performance."
                    },
                    {
                        "name": "assignee",
                        "value": "FPK-567"
                    },
                    {
                        "name": "priority",
                        "value": "medium"
                    },
                    {
                        "name": "due_date",
                        "value": "2023-11-20"
                    },
                    {
                        "name": "tags",
                        "value": [
                            "performance",
                            "database"
                        ]
                    }
                ]
            }
        ]
    },
    {
        "question": "We've identified an opportunity for a new enhancement in our project. Provide the details for creating this work item:\n\nType of Work: Enhancement\nTitle: Implement User Feedback Feature\nDescription: Enhance the system based on user feedback to improve overall user experience.\nAssignee: ABC-234\nPriority: High\nDue Date: 2023-12-10\nTags: ['user-feedback', 'enhancement']\n\nCould you create this enhancement?",
        "answer": [
            {
                "tool_name": "create_work_item",
                "arguments": [
                    {
                        "name": "work_item_type",
                        "value": "enhancement"
                    },
                    {
                        "name": "title",
                        "value": "Implement User Feedback Feature"
                    },
                    {
                        "name": "description",
                        "value": "Enhance the system based on user feedback to improve overall user experience."
                    },
                    {
                        "name": "assignee",
                        "value": "ABC-234"
                    },
                    {
                        "name": "priority",
                        "value": "high"
                    },
                    {
                        "name": "due_date",
                        "value": "2023-12-10"
                    },
                    {
                        "name": "tags",
                        "value": [
                            "user-feedback",
                            "enhancement"
                        ]
                    }
                ]
            }
        ]
    },
    {
        "question": "Can you update the status of task AMZ-234 to 'In Progress'?",
        "answer": [
            {
                "tool_name": "update_work_item_status",
                "arguments": [
                    {
                        "name": "work_item_id",
                        "value": "AMZ-234"
                    },
                    {
                        "name": "new_status",
                        "value": "In Progress"
                    }
                ]
            }
        ]
    },
    {
        "question": "Assign task KHD-567 to DAVE-987. Could you please update the status accordingly?",
        "answer": [
            {
                "tool_name": "update_work_item_status",
                "arguments": [
                    {
                        "name": "work_item_id",
                        "value": "KHD-567"
                    },
                    {
                        "name": "new_assignee",
                        "value": "DAVE-987"
                    }
                ]
            }
        ]
    },
    {
        "question": "Is it possible to adjust the estimated effort for task WZX-876 to 10 story points?",
        "answer": [
            {
                "tool_name": "update_work_item_status",
                "arguments": [
                    {
                        "name": "work_item_id",
                        "value": "WZX-876"
                    },
                    {
                        "name": "estimated_effort",
                        "value": 10
                    }
                ]
            }
        ]
    },
    {
        "question": "Considering dependencies on AMZ-456 and PRF-789, update the status of task IIT-123.",
        "answer": [
            {
                "tool_name": "update_work_item_status",
                "arguments": [
                    {
                        "name": "work_item_id",
                        "value": "IIT-123"
                    },
                    {
                        "name": "dependencies",
                        "value": ["AMZ-456", "PRF-789"]
                    }
                ]
            }
        ]
    },
    {
        "question": "Could you change the status of task TSK-789 to 'Done'?",
        "answer": [
            {
                "tool_name": "update_work_item_status",
                "arguments": [
                    {
                        "name": "work_item_id",
                        "value": "TSK-789"
                    },
                    {
                        "name": "new_status",
                        "value": "Done"
                    }
                ]
            }
        ]
    },
    {
        "question": "Task ABC-123 needs to be assigned to AMZ-456. Can you update the status accordingly?",
        "answer": [
            {
                "tool_name": "update_work_item_status",
                "arguments": [
                    {
                        "name": "work_item_id",
                        "value": "ABC-123"
                    },
                    {
                        "name": "new_assignee",
                        "value": "AMZ-456"
                    }
                ]
            }
        ]
    },
    {
        "question": "For task TSK-78, adjust the estimated effort to 12 story points. Can you do that?",
        "answer": [
            {
                "tool_name": "update_work_item_status",
                "arguments": [
                    {
                        "name": "work_item_id",
                        "value": "TSK-78"
                    },
                    {
                        "name": "estimated_effort",
                        "value": 12
                    }
                ]
            }
        ]
    },
    {
        "question": "Considering dependencies on TSK-78 and WRK-80, update the status of task KLS-123.",
        "answer": [
            {
                "tool_name": "update_work_item_status",
                "arguments": [
                    {
                        "name": "work_item_id",
                        "value": "KLS-123"
                    },
                    {
                        "name": "dependencies",
                        "value": ["TSK-78", "WRK-80"]
                    }
                ]
            }
        ]
    },
    {
        "question": "Let's kick off a new project called 'Project Delta'. The project involves building a data analytics platform. I've assigned 'XYZW-234' as the project lead, and the project should start on '2023-02-10'. The initial team members are ['QWER-234', 'XYZW-234']. The target completion date is '2023-08-15'. Can you proceed with creating this project?",
        "answer": [
            {
                "tool_name": "create_project",
                "arguments": [
                    {
                        "name": "project_name",
                        "value": "Project Delta"
                    },
                    {
                        "name": "project_description",
                        "value": "Building a data analytics platform."
                    },
                    {
                        "name": "project_lead",
                        "value": "XYZW-234"
                    },
                    {
                        "name": "start_date",
                        "value": "2023-02-10"
                    },
                    {
                        "name": "project_team",
                        "value": [
                            "XYZW-234",
                            "QWER-234"
                        ]
                    },
                    {
                        "name": "target_date",
                        "value": "2023-08-15"
                    }
                ]
            }
        ]
    },
    {
        "question": "I'm launching a new project named 'Project Omega'. The project aims to develop a machine learning model for predictive analytics. 'EVT-234' will lead the project, starting on '2023-04-05', with team members ['UVWX-234', 'LOC-234']. The target completion date is '2023-10-31'. Can you assist in setting up this project?",
        "answer": [
            {
                "tool_name": "create_project",
                "arguments": [
                    {
                        "name": "project_name",
                        "value": "Project Omega"
                    },
                    {
                        "name": "project_description",
                        "value": "Developing a machine learning model for predictive analytics."
                    },
                    {
                        "name": "project_lead",
                        "value": "EVT-234"
                    },
                    {
                        "name": "start_date",
                        "value": "2023-04-05"
                    },
                    {
                        "name": "project_team",
                        "value": [
                            "UVWX-234",
                            "LOC-234"
                        ]
                    },
                    {
                        "name": "target_date",
                        "value": "2023-10-31"
                    }
                ]
            }
        ]
    },
    {
        "question": "I have feedback on code review 'CR-456'. The feedback is 'Optimize this function for improved efficiency.' The code version is 'v3.0', and I'll assign a severity level of 'critical'. Can you help with this?",
        "answer": [
            {
                "tool_name": "code_review_feedback",
                "arguments": [
                    {
                        "name": "review_id",
                        "value": "CR-456"
                    },
                    {
                        "name": "feedback",
                        "value": "Optimize this function for improved efficiency."
                    },
                    {
                        "name": "code_version",
                        "value": "v3.0"
                    },
                    {
                        "name": "severity",
                        "value": "critical"
                    }
                ]
            }
        ]
    },
    {
        "question": "Generate a test execution report for test suite 'TS-789'.",
        "answer": [
            {
                "tool_name": "test_execution_report",
                "arguments": [
                    {
                        "name": "test_suite_id",
                        "value": "TS-789"
                    },
                    {
                        "name": "test_environment",
                        "value": "$$PREV[0]"
                    },
                    {
                        "name": "pass_fail_status",
                        "value": "$$PREV[0]"
                    },
                    {
                        "name": "test_case_types",
                        "value": "$$PREV[0]"
                    }
                ]
            }
        ]
    },
    {
        "question": "I need a test execution report for test case 'TC-789'.",
        "answer": [
            {
                "tool_name": "test_execution_report",
                "arguments": [
                    {
                        "name": "test_suite_id",
                        "value": "TC-789"
                    },
                    {
                        "name": "test_environment",
                        "value": "$$PREV[0]"
                    },
                    {
                        "name": "pass_fail_status",
                        "value": "$$PREV[0]"
                    },
                    {
                        "name": "test_case_types",
                        "value": "$$PREV[0]"
                    }
                ]
            }
        ]
    },
    {
        "question": "Initiate a new sprint for project 'PROJ-567'. The sprint should be titled 'Sprint 3', last for '2 weeks', focus on achieving 'Feature Enhancements', and have a maximum capacity of '40' Story Points. Include backlog items 'STORY-567' and 'STORY-234' in the sprint.",
        "answer": [
            {
                "tool_name": "create_sprint",
                "arguments": [
                    {
                        "name": "project_id",
                        "value": "PROJ-567"
                    },
                    {
                        "name": "sprint_name",
                        "value": "Sprint 3"
                    },
                    {
                        "name": "sprint_duration",
                        "value": "2 weeks"
                    },
                    {
                        "name": "sprint_goals",
                        "value": "Feature Enhancements"
                    },
                    {
                        "name": "sprint_capacity",
                        "value": 40
                    },
                    {
                        "name": "backlog_items",
                        "value": [
                            "STORY-567",
                            "STORY-234"
                        ]
                    }
                ]
            }
        ]
    },
    {
        "question": "We're initiating a sprint for project 'PROJ-345'. This sprint, named 'Sprint Alpha', will run for '4 weeks', focusing on 'Refactoring and Optimization'. The maximum capacity is set at '80' Story Points. Include backlog items 'STORY-345' and 'STORY-789' in the sprint. Can you set up this sprint?",
        "answer": [
            {
                "tool_name": "create_sprint",
                "arguments": [
                    {
                        "name": "project_id",
                        "value": "PROJ-345"
                    },
                    {
                        "name": "sprint_name",
                        "value": "Sprint Alpha"
                    },
                    {
                        "name": "sprint_duration",
                        "value": "4 weeks"
                    },
                    {
                        "name": "sprint_goals",
                        "value": "Refactoring and Optimization"
                    },
                    {
                        "name": "sprint_capacity",
                        "value": 80
                    },
                    {
                        "name": "backlog_items",
                        "value": [
                            "STORY-345",
                            "STORY-789"
                        ]
                    }
                ]
            }
        ]
    },
    {
        "question": "We've got a task with ID 'TASK-234' that requires assignment to 'DEVU-567'. This task, categorized as high-priority, must be completed by '2024-01-10'. Can you handle this assignment?",
        "answer": [
            {
                "tool_name": "assign_work_item",
                "arguments": [
                    {
                        "name": "work_item_id",
                        "value": "TASK-234"
                    },
                    {
                        "name": "assignee",
                        "value": "DEVU-567"
                    },
                    {
                        "name": "priority",
                        "value": "high"
                    },
                    {
                        "name": "due_date",
                        "value": "2024-01-10"
                    },
                    {
                        "name": "work_item_type",
                        "value": "task"
                    }
                ]
            }
        ]
    },
    {
        "question": "A new task 'WRK-80' has been identified, and it requires assignment to 'AMZ-456'. This task is marked as high-priority and needs completion by '2023-12-20'. Could you manage this assignment?",
        "answer": [
            {
                "tool_name": "assign_work_item",
                "arguments": [
                    {
                        "name": "work_item_id",
                        "value": "WRK-80"
                    },
                    {
                        "name": "assignee",
                        "value": "AMZ-456"
                    },
                    {
                        "name": "priority",
                        "value": "high"
                    },
                    {
                        "name": "due_date",
                        "value": "2023-12-20"
                    },
                    {
                        "name": "work_item_type",
                        "value": "task"
                    }
                ]
            }
        ]
    },
    {
        "question": "We're initiating an automated workflow triggered by 'Bug fix approved' events. This workflow should execute specific actions, notify 'DEVU-567', and maintain an actions log. Can you help set up this workflow?",
        "answer": [
            {
                "tool_name": "automate_workflow",
                "arguments": [
                    {
                        "name": "trigger_event",
                        "value": "Bug fix approved"
                    },
                    {
                        "name": "workflow_actions",
                        "value": [
                            "Update Bug Status",
                            "Send Email Notification"
                        ]
                    },
                    {
                        "name": "notifications",
                        "value": [
                            "DEVU-567"
                        ]
                    },
                    {
                        "name": "actions_log",
                        "value": true
                    }
                ]
            }
        ]
    },
    {
        "question": "We have a new workflow to automate triggered by 'Feature request submitted' events. This workflow should execute specific actions, notify 'DEVU-789' and 'DEVU-234', and maintain an actions log. Can you assist in setting up this workflow?",
        "answer": [
            {
                "tool_name": "automate_workflow",
                "arguments": [
                    {
                        "name": "trigger_event",
                        "value": "Feature request submitted"
                    },
                    {
                        "name": "workflow_actions",
                        "value": [
                            "Evaluate Feature Request",
                            "Send Notification to Product Team"
                        ]
                    },
                    {
                        "name": "notifications",
                        "value": [
                            "DEVU-789",
                            "DEVU-234"
                        ]
                    },
                    {
                        "name": "actions_log",
                        "value": true
                    }
                ]
            }
        ]
    }   
]